sbmlcore/AminoAcidProperties.py
sbmlcore/DeepDDG.py
sbmlcore/ExternalCode.py
sbmlcore/FeaturesDataFrame.py
sbmlcore/Misc.py
sbmlcore/RaSP.py
sbmlcore/ResidueDepth.py
sbmlcore/StructuralDistances.py
sbmlcore/TempFactors.py
sbmlcore/TrajectoryDihedrals.py
sbmlcore/TrajectoryDistances.py
sbmlcore/__init__.py
sbmlcore/data/rogov.csv
sbmlcore-0.2.8.dist-info/LICENSE
sbmlcore-0.2.8.dist-info/METADATA
sbmlcore-0.2.8.dist-info/WHEEL
sbmlcore-0.2.8.dist-info/top_level.txt
sbmlcore-0.2.8.dist-info/RECORD
