Metadata-Version: 2.1
Name: sbmlcore
Version: 0.2.8
Summary: Constructs core features table for the application to machine learning models
Home-page: https://github.com/fowler-lab/sbmlcore
Author: Philip W Fowler and Charlotte I Lynch and Dylan Adlard
Author-email: philip.fowler@ndm.ox.ac.uk
License: MIT
Project-URL: Documentation, https://github.com/fowler-lab/sbmlcore
Project-URL: CI, https://github.com/fowler-lab/sbmlcore/actions
Project-URL: Source, https://github.com/fowler-lab/sbmlcore
Project-URL: Tracker, https://github.com/fowler-lab/sbmlcore/issues
Classifier: Environment :: Console
Classifier: Intended Audience :: Science/Research
Classifier: License :: OSI Approved :: MIT License
Classifier: Natural Language :: English
Classifier: Operating System :: POSIX :: Linux
Classifier: Operating System :: MacOS :: MacOS X
Classifier: Programming Language :: Python :: 3
Requires-Python: >=3.6
License-File: LICENSE
Requires-Dist: pandas
Requires-Dist: MDAnalysis
Requires-Dist: freesasa
Requires-Dist: pytest
Requires-Dist: pytest-cov
Requires-Dist: BioPython
